tcpnonblock/__init__.py
tcpnonblock/client.py
tcpnonblock/instance.py
tcpnonblock/server.py
tcpnonblock/utils.py
tcpnonblock-0.1.1.dist-info/LICENSE
tcpnonblock-0.1.1.dist-info/METADATA
tcpnonblock-0.1.1.dist-info/WHEEL
tcpnonblock-0.1.1.dist-info/top_level.txt
tcpnonblock-0.1.1.dist-info/RECORD
