Metadata-Version: 2.1
Name: tcpnonblock
Version: 0.1.1
Summary: A Simple Implementation of Non-Blocking TCP Socket Server.
Home-page: https://github.com/SamHDev/tcpnonblock
Author: SamHDev
Author-email: sam02h.huddart@gmail.com
License: UNKNOWN
Platform: UNKNOWN
Classifier: Programming Language :: Python :: 3
Classifier: Operating System :: OS Independent
